odoo10_addon_hr_timesheet_no_closed_project_task-10.0.1.0.0.99.dev10-py3.8-nspkg.pth
odoo/addons/hr_timesheet_no_closed_project_task/README.rst
odoo/addons/hr_timesheet_no_closed_project_task/__init__.py
odoo/addons/hr_timesheet_no_closed_project_task/__manifest__.py
odoo/addons/hr_timesheet_no_closed_project_task/i18n/cs_CZ.po
odoo/addons/hr_timesheet_no_closed_project_task/i18n/es.po
odoo/addons/hr_timesheet_no_closed_project_task/i18n/fr.po
odoo/addons/hr_timesheet_no_closed_project_task/i18n/hr_timesheet_no_closed_project_task.pot
odoo/addons/hr_timesheet_no_closed_project_task/i18n/it.po
odoo/addons/hr_timesheet_no_closed_project_task/models/__init__.py
odoo/addons/hr_timesheet_no_closed_project_task/models/project_task.py
odoo/addons/hr_timesheet_no_closed_project_task/security/ir.model.access.csv
odoo/addons/hr_timesheet_no_closed_project_task/static/description/icon.png
odoo/addons/hr_timesheet_no_closed_project_task/static/src/js/timesheet.js
odoo/addons/hr_timesheet_no_closed_project_task/views/account_analytic_line.xml
odoo/addons/hr_timesheet_no_closed_project_task/views/hr_timesheet_no_closed_project_task.xml
odoo/addons/hr_timesheet_no_closed_project_task/views/hr_timesheet_sheet_sheet.xml
odoo10_addon_hr_timesheet_no_closed_project_task-10.0.1.0.0.99.dev10.dist-info/METADATA
odoo10_addon_hr_timesheet_no_closed_project_task-10.0.1.0.0.99.dev10.dist-info/WHEEL
odoo10_addon_hr_timesheet_no_closed_project_task-10.0.1.0.0.99.dev10.dist-info/namespace_packages.txt
odoo10_addon_hr_timesheet_no_closed_project_task-10.0.1.0.0.99.dev10.dist-info/top_level.txt
odoo10_addon_hr_timesheet_no_closed_project_task-10.0.1.0.0.99.dev10.dist-info/RECORD
