Metadata-Version: 2.1
Name: odoo10-addon-hr-timesheet-no-closed-project-task
Version: 10.0.1.0.0.99.dev10
Summary: Prevent to select closed project or task on timesheet line
Home-page: https://github.com/OCA/hr-timesheet
Author: ACSONE SA/NV,Odoo Community Association (OCA)
Author-email: support@odoo-community.org
License: AGPL-3
Platform: UNKNOWN
Classifier: Programming Language :: Python
Classifier: Framework :: Odoo
Classifier: Framework :: Odoo :: 10.0
Classifier: License :: OSI Approved :: GNU Affero General Public License v3
Requires-Python: ~=2.7
Requires-Dist: odoo10-addon-hr-timesheet-task
Requires-Dist: odoo10-addon-project-stage-closed
Requires-Dist: odoo (<10.1dev,>=10.0)
